retrylite/__init__.py
retrylite/_async.py
retrylite/_sync.py
retrylite/py.typed
retrylite-0.1.2.dist-info/METADATA
retrylite-0.1.2.dist-info/WHEEL
retrylite-0.1.2.dist-info/licenses/LICENSE
retrylite-0.1.2.dist-info/RECORD
