Metadata-Version: 2.4
Name: retrylite
Version: 0.1.2
Summary: Zero-dependency retry decorator (sync & async)
Project-URL: Homepage, https://github.com/moehandi/retrylite
Project-URL: Documentation, https://github.com/moehandi/retrylite#readme
Project-URL: Repository, https://github.com/moehandi/retrylite.git
Project-URL: Changelog, https://github.com/moehandi/retrylite/blob/main/CHANGELOG.md
Author-email: "M. Andi Saputra" <moehandi@gmail.com>
License: MIT
License-File: LICENSE
Keywords: async,backoff,circuit-breaker,resilience,retry
Classifier: Development Status :: 5 - Production/Stable
Classifier: Intended Audience :: Developers
Classifier: License :: OSI Approved :: MIT License
Classifier: Programming Language :: Python :: 3.9
Classifier: Programming Language :: Python :: 3.10
Classifier: Programming Language :: Python :: 3.11
Classifier: Programming Language :: Python :: 3.12
Classifier: Programming Language :: Python :: 3.13
Classifier: Topic :: Software Development :: Libraries :: Python Modules
Requires-Python: >=3.9
Provides-Extra: metrics
Requires-Dist: opentelemetry-api>=1.20; extra == 'metrics'
Requires-Dist: prometheus-client>=0.19; extra == 'metrics'
